mztabpy-0.0.1.data/scripts/mztabpy_click.py
tests/__init__.py
tests/test_mztabpy.py
mztabpy-0.0.1.dist-info/LICENSE
mztabpy-0.0.1.dist-info/METADATA
mztabpy-0.0.1.dist-info/WHEEL
mztabpy-0.0.1.dist-info/entry_points.txt
mztabpy-0.0.1.dist-info/top_level.txt
mztabpy-0.0.1.dist-info/RECORD
