Metadata-Version: 2.1
Name: mztabpy
Version: 0.0.1
Summary: Python package to handle mztab files
Home-page: https://github.com/bigbio/mztabpy/
Download-URL: https://github.com/bigbio/mztabpy/
Author: Yasset Perez-Riverol
Author-email: ypriverol@gmail.com
License: MIT
Keywords: Proteomics,Label-free,quality control,MultiQC
Classifier: Development Status :: 4 - Beta
Classifier: Environment :: Console
Classifier: Environment :: Web Environment
Classifier: Intended Audience :: Science/Research
Classifier: License :: OSI Approved :: MIT License
Classifier: Natural Language :: English
Classifier: Operating System :: MacOS :: MacOS X
Classifier: Operating System :: POSIX
Classifier: Operating System :: Unix
Classifier: Programming Language :: Python
Classifier: Programming Language :: JavaScript
Classifier: Topic :: Scientific/Engineering
Classifier: Topic :: Scientific/Engineering :: Bio-Informatics
Classifier: Topic :: Scientific/Engineering :: Visualization
License-File: LICENSE
Requires-Dist: tables
Requires-Dist: pandas
Requires-Dist: Click
